{
  "properties": [
    {
      "name": "kafka.consumer.autoOffsetReset",
      "type": "java.lang.String",
      "description": "Description for kafka.consumer.autoOffsetReset."
    },
    {
      "name": "kafka.consumer.maxPollRecords",
      "type": "java.lang.String",
      "description": "Description for kafka.consumer.maxPollRecords."
    },
    {
      "name": "kafka.consumer.sessionTimeoutMs",
      "type": "java.lang.String",
      "description": "Description for kafka.consumer.sessionTimeoutMs."
    },
    {
      "name": "kafka.consumer.autoCommitIntervalMs",
      "type": "java.lang.String",
      "description": "Description for kafka.consumer.autoCommitIntervalMs."
    },
    {
      "name": "kafka.consumer.enableAutoCommit",
      "type": "java.lang.String",
      "description": "Description for kafka.consumer.enableAutoCommit."
    },
    {
      "name": "kafka.consumer.groupId",
      "type": "java.lang.String",
      "description": "Description for kafka.consumer.groupId."
    },
    {
      "name": "kafka.consumer.bootstrapServers",
      "type": "java.lang.String",
      "description": "Description for kafka.consumer.bootstrapServers."
    },
    {
      "name": "kafka.producer.bufferMemory",
      "type": "java.lang.String",
      "description": "Description for kafka.producer.bufferMemory."
    },
    {
      "name": "kafka.producer.lingerMs",
      "type": "java.lang.String",
      "description": "Description for kafka.producer.lingerMs."
    },
    {
      "name": "kafka.producer.batchSize",
      "type": "java.lang.String",
      "description": "Description for kafka.producer.batchSize."
    },
    {
      "name": "kafka.producer.retries",
      "type": "java.lang.String",
      "description": "Description for kafka.producer.retries."
    },
    {
      "name": "kafka.producer.bootstrapServers",
      "type": "java.lang.String",
      "description": "Description for kafka.producer.bootstrapServers."
    },
    {
      "name": "server.session-timeout",
      "type": "java.lang.String",
      "description": "Description for server.session-timeout."
    }
  ]
}